common/__init__.py
common/base.py
common/config.py
common/decorators.py
common/exceptions.py
common/utils.py
db/__init__.py
db/core.py
log/__init__.py
log/logger.py
log/server_log.py
templates/__init__.py
templates/templates.py
messenger_server_smozheiko-0.1.0.dist-info/METADATA
messenger_server_smozheiko-0.1.0.dist-info/WHEEL
messenger_server_smozheiko-0.1.0.dist-info/top_level.txt
messenger_server_smozheiko-0.1.0.dist-info/RECORD
